NNstyle/__init__.py
NNstyle/core/ArrowImage.py
NNstyle/core/LayerImage.py
NNstyle/core/NNstyle.py
NNstyle/core/__init__.py
NNstyle/core/base.py
NNstyle-0.0.2.dist-info/METADATA
NNstyle-0.0.2.dist-info/WHEEL
NNstyle-0.0.2.dist-info/top_level.txt
NNstyle-0.0.2.dist-info/RECORD
