Metadata-Version: 2.1
Name: NNstyle
Version: 0.0.2
Summary: draw neural network architecture
Home-page: http://www.nanguoyu.com
Author: nanguoyu
Author-email: admin@nanguoyu.com
License: MIT Licence
Keywords: pip,NNstyle,NN-architecture
Platform: any
Requires-Dist: Pillow
